{
  "a6716154a87c000d4d361242a65cb0b3": {
    "date": "2026-06-19",
    "worker": "Abdul Latif",
    "sent_ts": 1781847665,
    "acknowledged": false,
    "category": "INCIDENT REPORT \u2014 DESCRIPTION TOO BRIEF",
    "client": "Incident Report",
    "pending": false
  },
  "ddce2c6c13eeed7da92bf62f24abff67": {
    "date": "2026-06-19",
    "worker": "Abdul Latif",
    "sent_ts": 1781847665,
    "acknowledged": false,
    "category": "INCIDENT REPORT \u2014 DESCRIPTION TOO BRIEF",
    "client": "Incident Report",
    "pending": false
  },
  "1fab20a4cdb2bf0efcc88f97b7127c13": {
    "date": "2026-06-19",
    "worker": "Abdul Latif",
    "sent_ts": 1781847665,
    "acknowledged": false,
    "category": "INCIDENT REPORT \u2014 MISSING WITNESS/NOTIFICATION",
    "client": "Incident Report",
    "pending": false
  },
  "57cd05d65d8d160f3544fa15c91f9e2f": {
    "date": "2026-06-19",
    "worker": "Abdul Latif",
    "sent_ts": 1781847665,
    "acknowledged": false,
    "category": "INCIDENT REPORT \u2014 MISSING WITNESS/NOTIFICATION",
    "client": "Incident Report",
    "pending": false
  },
  "a10433f3e4f9711040677902437cb4ad": {
    "date": "2026-06-19",
    "worker": "Abdul Latif",
    "sent_ts": 1781847665,
    "acknowledged": false,
    "category": "PENDING AMENDMENT -- WORKER NOTICE",
    "client": "Evan Gatt",
    "pending": true
  },
  "db8b74e526a9e5ee8ec1f0cd3baed657": {
    "date": "2026-06-19",
    "worker": "Abdul Latif",
    "sent_ts": 1781847665,
    "acknowledged": false,
    "category": "PENDING AMENDMENT -- WORKER NOTICE",
    "client": "Evan Gatt",
    "pending": true
  },
  "6ab4cab6974429413ed38b5ffbd51c07": {
    "date": "2026-06-19",
    "worker": "Abdul Latif",
    "sent_ts": 1781847665,
    "acknowledged": false,
    "category": "PENDING AMENDMENT -- WORKER NOTICE",
    "client": "Evan Gatt",
    "pending": true
  },
  "acf039a8b784dabd3ca4473f913e14b5": {
    "date": "2026-06-19",
    "worker": "Ali Saaram",
    "sent_ts": 1781847665,
    "acknowledged": false,
    "category": "AUTO CLOCK-OUT",
    "client": "Kallan Jordan",
    "pending": false
  },
  "642dfc8fbee3293a4516e9d1b3edaa68": {
    "date": "2026-06-19",
    "worker": "Ali Saaram",
    "sent_ts": 1781847665,
    "acknowledged": false,
    "category": "AUTO CLOCK-OUT",
    "client": "Kallan Jordan",
    "pending": false
  },
  "8d6efc208a2c25263451ffd538f0f763": {
    "date": "2026-06-19",
    "worker": "Ali Saaram",
    "sent_ts": 1781847665,
    "acknowledged": false,
    "category": "INCIDENT REPORT \u2014 DESCRIPTION TOO BRIEF",
    "client": "Kallan Incident Report",
    "pending": false
  },
  "fbb4ad3cc41c26a044eb50b29e575e0b": {
    "date": "2026-06-19",
    "worker": "Ali Saaram",
    "sent_ts": 1781847665,
    "acknowledged": false,
    "category": "INCIDENT REPORT \u2014 MISSING WITNESS/NOTIFICATION",
    "client": "Kallan Incident Report",
    "pending": false
  },
  "97982b5c2aa2b233bda57cfddee42a0f": {
    "date": "2026-06-19",
    "worker": "Ali Saaram",
    "sent_ts": 1781847665,
    "acknowledged": false,
    "category": "OVERBILLING RISK -- HOURS EXCEED ROSTER",
    "client": "(all clients)",
    "pending": false
  },
  "27a89a0c0da2322fd77a41f0b6193e38": {
    "date": "2026-06-19",
    "worker": "Ali Saaram",
    "sent_ts": 1781847665,
    "acknowledged": false,
    "category": "PENDING AMENDMENT -- WORKER NOTICE",
    "client": "Kallan Jordan",
    "pending": true
  },
  "04134dbe8602f3384c13aa9fd31e04a8": {
    "date": "2026-06-19",
    "worker": "Ali Saaram",
    "sent_ts": 1781847665,
    "acknowledged": false,
    "category": "PENDING AMENDMENT -- WORKER NOTICE",
    "client": "Kallan Jordan",
    "pending": true
  },
  "73d0d87105f7c7c50fbfafe3ca3b9f37": {
    "date": "2026-06-19",
    "worker": "Ali Saaram",
    "sent_ts": 1781847665,
    "acknowledged": false,
    "category": "PENDING AMENDMENT -- WORKER NOTICE",
    "client": "Kallan Jordan",
    "pending": true
  },
  "a72a76f584f07b928289d04f1a9729ab": {
    "date": "2026-06-19",
    "worker": "Hajar El Hassan",
    "sent_ts": 1781847665,
    "acknowledged": false,
    "category": "PENDING AMENDMENT -- WORKER NOTICE",
    "client": "Nicole Loveless",
    "pending": true
  },
  "b618b59a558a04e69b8f8edaa8a312ff": {
    "date": "2026-06-19",
    "worker": "Hajar El Hassan",
    "sent_ts": 1781847665,
    "acknowledged": false,
    "category": "PENDING AMENDMENT -- WORKER NOTICE",
    "client": "Mathew B Worden",
    "pending": true
  },
  "dafa5ec8a6b210196071a9bfbefb69b3": {
    "date": "2026-06-19",
    "worker": "Ikram Mohammad",
    "sent_ts": 1781847665,
    "acknowledged": false,
    "category": "NO CLOCK-IN",
    "client": "Xavier Putchakayla",
    "pending": false
  },
  "817537dd5d8a9b7f7810613b1c41a83f": {
    "date": "2026-06-19",
    "worker": "Irfanullah Zamir",
    "sent_ts": 1781847665,
    "acknowledged": false,
    "category": "LATE CLOCK-IN",
    "client": "Kallan Jordan",
    "pending": false
  },
  "d752660e717155c0fc3a4da6cb3cc1bc": {
    "date": "2026-06-19",
    "worker": "Irfanullah Zamir",
    "sent_ts": 1781847665,
    "acknowledged": false,
    "category": "AUTO CLOCK-OUT",
    "client": "Kallan Jordan",
    "pending": false
  },
  "4246839ad8a2a24ef11f80a5d9335bc4": {
    "date": "2026-06-19",
    "worker": "Irfanullah Zamir",
    "sent_ts": 1781847665,
    "acknowledged": false,
    "category": "PENDING AMENDMENT -- WORKER NOTICE",
    "client": "Kallan Jordan",
    "pending": true
  },
  "6a4797eaf0003fc81f82cd7b52c7c680": {
    "date": "2026-06-19",
    "worker": "Mayada El Hassan",
    "sent_ts": 1781847665,
    "acknowledged": false,
    "category": "EARLY CLOCK-OUT",
    "client": "Nada Haliem",
    "pending": false
  },
  "078e4a22320991e0a057bf08938f8462": {
    "date": "2026-06-19",
    "worker": "Mayada El Hassan",
    "sent_ts": 1781847665,
    "acknowledged": false,
    "category": "PENDING AMENDMENT -- WORKER NOTICE",
    "client": "Nada Haliem",
    "pending": true
  },
  "fb1974ead2026d8c312718b2f067e120": {
    "date": "2026-06-19",
    "worker": "Mohamed Liban",
    "sent_ts": 1781847665,
    "acknowledged": false,
    "category": "EARLY CLOCK-OUT",
    "client": "Kallan Jordan",
    "pending": false
  },
  "15f87f6c4813dc24ba0b6a95f01024f7": {
    "date": "2026-06-19",
    "worker": "Mohamed Liban",
    "sent_ts": 1781847665,
    "acknowledged": false,
    "category": "AUTO CLOCK-OUT",
    "client": "Kallan Jordan",
    "pending": false
  },
  "557dec76613dbb48d51fa1bf2018dd8c": {
    "date": "2026-06-19",
    "worker": "Mohamed Liban",
    "sent_ts": 1781847665,
    "acknowledged": false,
    "category": "INCIDENT REPORT \u2014 FAILS NDIS STANDARD",
    "client": "Kallan Incident Report",
    "pending": false
  },
  "538f22739721c5b76ea4b1c17ddcc3f4": {
    "date": "2026-06-19",
    "worker": "Mohamed Liban",
    "sent_ts": 1781847665,
    "acknowledged": false,
    "category": "INCIDENT REPORT \u2014 MISSING WITNESS/NOTIFICATION",
    "client": "Kallan Incident Report",
    "pending": false
  },
  "f744d3ad1784db289c0845d78e56af8e": {
    "date": "2026-06-19",
    "worker": "Mohamed Liban",
    "sent_ts": 1781847665,
    "acknowledged": false,
    "category": "LATE CLOCK-IN",
    "client": "Kallan Jordan",
    "pending": false
  },
  "06bdf35fd5c94952b9223224ef712963": {
    "date": "2026-06-19",
    "worker": "Mohamed Liban",
    "sent_ts": 1781847665,
    "acknowledged": false,
    "category": "OVERBILLING RISK -- HOURS EXCEED ROSTER",
    "client": "(all clients)",
    "pending": false
  },
  "27f26a0cdde97b6b7417786c941c5798": {
    "date": "2026-06-19",
    "worker": "Mohamed Liban",
    "sent_ts": 1781847665,
    "acknowledged": false,
    "category": "PENDING AMENDMENT -- WORKER NOTICE",
    "client": "Kallan Jordan",
    "pending": true
  },
  "abc0826576ac3d76c6aaba8823d3b701": {
    "date": "2026-06-19",
    "worker": "Mohamed Liban",
    "sent_ts": 1781847665,
    "acknowledged": false,
    "category": "PENDING AMENDMENT -- WORKER NOTICE",
    "client": "Kallan Jordan",
    "pending": true
  },
  "60ff2f293ad273910fcbbf7fd5690a75": {
    "date": "2026-06-19",
    "worker": "Mohamed Liban",
    "sent_ts": 1781847665,
    "acknowledged": false,
    "category": "PENDING AMENDMENT -- WORKER NOTICE",
    "client": "Kallan Jordan",
    "pending": true
  },
  "f629046ce2532cbf1e33d7b8bf7f5642": {
    "date": "2026-06-19",
    "worker": "Peter Eronmwon",
    "sent_ts": 1781847665,
    "acknowledged": false,
    "category": "EARLY CLOCK-OUT",
    "client": "Joshua Gatt",
    "pending": false
  },
  "603e76590172b00be8209ba8dbb44b92": {
    "date": "2026-06-19",
    "worker": "Peter Eronmwon",
    "sent_ts": 1781847665,
    "acknowledged": false,
    "category": "OVERBILLING RISK -- HOURS EXCEED ROSTER",
    "client": "(all clients)",
    "pending": false
  },
  "f3de6f7a66a010561d90c483788057a6": {
    "date": "2026-06-19",
    "worker": "Peter Eronmwon",
    "sent_ts": 1781847665,
    "acknowledged": false,
    "category": "PENDING AMENDMENT -- WORKER NOTICE",
    "client": "Joshua Gatt",
    "pending": true
  },
  "20494fb6f2a2680b3041fe91c98ff9e7": {
    "date": "2026-06-19",
    "worker": "Peter Eronmwon",
    "sent_ts": 1781847665,
    "acknowledged": false,
    "category": "PENDING AMENDMENT -- WORKER NOTICE",
    "client": "John Auzagelis",
    "pending": true
  },
  "8e889b1674a72656f38dac9e06ca7833": {
    "date": "2026-06-19",
    "worker": "Peter Eronmwon",
    "sent_ts": 1781847665,
    "acknowledged": false,
    "category": "PENDING AMENDMENT -- WORKER NOTICE",
    "client": "Joshua Gatt",
    "pending": true
  },
  "d731b11b955dd6216dfd6a73a26ca22e": {
    "date": "2026-06-19",
    "worker": "Roja Mehmood",
    "sent_ts": 1781847665,
    "acknowledged": false,
    "category": "NO CLOCK-IN",
    "client": "Kallan Jordan",
    "pending": false
  },
  "0f3ca06e1b244f7df9cb54999ef69dfe": {
    "date": "2026-06-19",
    "worker": "Roja Mehmood",
    "sent_ts": 1781847665,
    "acknowledged": false,
    "category": "NO CLOCK-IN",
    "client": "Joshua Gatt",
    "pending": false
  },
  "3d467cdca225ed6f38c1939f8bb201e1": {
    "date": "2026-06-19",
    "worker": "Roja Mehmood",
    "sent_ts": 1781847665,
    "acknowledged": false,
    "category": "INCIDENT REPORT \u2014 DESCRIPTION TOO BRIEF",
    "client": "Kallan Incident Report",
    "pending": false
  },
  "359d91705fd47d0e787ce078ed48e813": {
    "date": "2026-06-19",
    "worker": "Roja Mehmood",
    "sent_ts": 1781847665,
    "acknowledged": false,
    "category": "INCIDENT REPORT \u2014 MISSING WITNESS/NOTIFICATION",
    "client": "Kallan Incident Report",
    "pending": false
  },
  "dc65a5177360f8ca9d16487b06e49031": {
    "date": "2026-06-19",
    "worker": "(team)",
    "category": "FORM FREQUENCY -- JOHN",
    "client": "John",
    "pending": false
  },
  "156af89327c768c5889ef3652f952948": {
    "date": "2026-06-19",
    "worker": "(team)",
    "category": "FORM FREQUENCY -- JOSHUA",
    "client": "Joshua Gatt",
    "pending": false
  },
  "c4b1adb05031d1147cf2f59bc1d02d8e": {
    "date": "2026-06-19",
    "worker": "(team)",
    "category": "FORM FREQUENCY -- NADA",
    "client": "Nada Haliem",
    "pending": false
  },
  "8e0a56b0b4d070e05c8a093237f316f2": {
    "date": "2026-06-19",
    "worker": "(team)",
    "category": "FORM FREQUENCY -- NICOLE",
    "client": "Nicole Loveless",
    "pending": false
  },
  "ca46d682b93e7713c50c14eafb2cfbb9": {
    "date": "2026-06-19",
    "worker": "(team)",
    "category": "MISSING FORM -- EVAN",
    "client": "Evan Gatt",
    "pending": false
  },
  "a813192de908add3a50f2c0df41fe8ac": {
    "date": "2026-06-19",
    "worker": "(team)",
    "category": "MISSING FORM -- KALLAN",
    "client": "Kallan Jordan",
    "pending": false
  },
  "f6e4fc5e7d8391c6412f0f0a315435fc": {
    "date": "2026-06-19",
    "worker": "(team)",
    "category": "MISSING FORM -- KALLAN",
    "client": "Kallan Jordan",
    "pending": false
  },
  "4b29f2f85ae05124fc053459f8cc833b": {
    "date": "2026-06-19",
    "worker": "Ali Saaram",
    "category": "UNDERSTAFFED -- RATIO BREACH",
    "client": "Kallan Jordan",
    "pending": false
  },
  "6d24e263e6c03cdb24435eb166afb411": {
    "date": "2026-06-19",
    "worker": "Ali Saaram",
    "category": "UNDERSTAFFED -- RATIO BREACH",
    "client": "Kallan Jordan",
    "pending": false
  },
  "a429523a14baac32a840d279afd320d9": {
    "date": "2026-06-19",
    "worker": "Irfanullah Zamir",
    "category": "UNDERSTAFFED -- RATIO BREACH",
    "client": "Kallan Jordan",
    "pending": false
  },
  "12b8a1f6f4b4acb5f9e4889e8ca384ef": {
    "date": "2026-06-19",
    "worker": "Mohamed Liban",
    "category": "UNDERSTAFFED -- RATIO BREACH",
    "client": "Kallan Jordan",
    "pending": false
  },
  "5188aece37e4a76c7b74d82e64c8637f": {
    "date": "2026-06-19",
    "worker": "Abdul Latif",
    "category": "PENDING AMENDMENT -- REVIEW REQUIRED",
    "client": "Evan Gatt",
    "pending": true
  },
  "c90accd4c966b9da9965c2bdefebc482": {
    "date": "2026-06-19",
    "worker": "Abdul Latif",
    "category": "PENDING AMENDMENT -- REVIEW REQUIRED",
    "client": "Evan Gatt",
    "pending": true
  },
  "6d6c435afb3358abf2933414eed36084": {
    "date": "2026-06-19",
    "worker": "Abdul Latif",
    "category": "PENDING AMENDMENT -- REVIEW REQUIRED",
    "client": "Evan Gatt",
    "pending": true
  },
  "7efe5e7055d81e1070e1def5960983ee": {
    "date": "2026-06-19",
    "worker": "Ali Saaram",
    "category": "PENDING AMENDMENT -- REVIEW REQUIRED",
    "client": "Kallan Jordan",
    "pending": true
  },
  "0845ce6eb01149ef5642b9c6337e0e37": {
    "date": "2026-06-19",
    "worker": "Ali Saaram",
    "category": "PENDING AMENDMENT -- REVIEW REQUIRED",
    "client": "Kallan Jordan",
    "pending": true
  },
  "dd684b5ff9bc878d9f2b86f401670934": {
    "date": "2026-06-19",
    "worker": "Ali Saaram",
    "category": "PENDING AMENDMENT -- REVIEW REQUIRED",
    "client": "Kallan Jordan",
    "pending": true
  },
  "5d60a99ecb011adf307482b2814e9f4b": {
    "date": "2026-06-19",
    "worker": "Hajar El Hassan",
    "category": "PENDING AMENDMENT -- REVIEW REQUIRED",
    "client": "Nicole Loveless",
    "pending": true
  },
  "1bf282845f52a20a7c20edf0306aff4e": {
    "date": "2026-06-19",
    "worker": "Hajar El Hassan",
    "category": "PENDING AMENDMENT -- REVIEW REQUIRED",
    "client": "Mathew B Worden",
    "pending": true
  },
  "f24483748904c389491138cbc8881db7": {
    "date": "2026-06-19",
    "worker": "Irfanullah Zamir",
    "category": "PENDING AMENDMENT -- REVIEW REQUIRED",
    "client": "Kallan Jordan",
    "pending": true
  },
  "8a0d41dde8e7f85f3bfddd11f11f9966": {
    "date": "2026-06-19",
    "worker": "Mayada El Hassan",
    "category": "PENDING AMENDMENT -- REVIEW REQUIRED",
    "client": "Nada Haliem",
    "pending": true
  },
  "9b44c7946a4a07cee1b36842273e2d27": {
    "date": "2026-06-19",
    "worker": "Mohamed Liban",
    "category": "PENDING AMENDMENT -- REVIEW REQUIRED",
    "client": "Kallan Jordan",
    "pending": true
  },
  "59df9eaf4139ffdfdbe73bfc233a2069": {
    "date": "2026-06-19",
    "worker": "Mohamed Liban",
    "category": "PENDING AMENDMENT -- REVIEW REQUIRED",
    "client": "Kallan Jordan",
    "pending": true
  },
  "7a700a844c2481f7d428ade9f569325e": {
    "date": "2026-06-19",
    "worker": "Mohamed Liban",
    "category": "PENDING AMENDMENT -- REVIEW REQUIRED",
    "client": "Kallan Jordan",
    "pending": true
  },
  "fb40faf31fee56eb2201b4bc2e17d3db": {
    "date": "2026-06-19",
    "worker": "Peter Eronmwon",
    "category": "PENDING AMENDMENT -- REVIEW REQUIRED",
    "client": "Joshua Gatt",
    "pending": true
  },
  "46d1a5369362882e398c4d8b68265bbe": {
    "date": "2026-06-19",
    "worker": "Peter Eronmwon",
    "category": "PENDING AMENDMENT -- REVIEW REQUIRED",
    "client": "John Auzagelis",
    "pending": true
  },
  "54aec87651f04879905ded5fdac1b243": {
    "date": "2026-06-19",
    "worker": "Peter Eronmwon",
    "category": "PENDING AMENDMENT -- REVIEW REQUIRED",
    "client": "Joshua Gatt",
    "pending": true
  }
}